arcade_posthog_api/__init__.py
arcade_posthog_api/moar/Posthog.json
arcade_posthog_api/moar/openapi.json
arcade_posthog_api/tools/__init__.py
arcade_posthog_api/tools/request_body_schemas.py
arcade_posthog_api/wrapper_tools/AddDashboardCollaborator.json
arcade_posthog_api/wrapper_tools/AddDataColorTheme.json
arcade_posthog_api/wrapper_tools/AddPersonsFunnelCorrelation.json
arcade_posthog_api/wrapper_tools/AddPersonsToStaticCohort.json
arcade_posthog_api/wrapper_tools/AddSessionRecordingToPlaylist.json
arcade_posthog_api/wrapper_tools/AddWarehouseSavedQuery.json
arcade_posthog_api/wrapper_tools/AddWarehouseTable.json
arcade_posthog_api/wrapper_tools/AppendTaskRunLogs.json
arcade_posthog_api/wrapper_tools/CancelBatchExportBackfill.json
arcade_posthog_api/wrapper_tools/CancelBatchExportRun.json
arcade_posthog_api/wrapper_tools/CancelEmailChangeRequest.json
arcade_posthog_api/wrapper_tools/CancelInsightCreation.json
arcade_posthog_api/wrapper_tools/CancelInvitation.json
arcade_posthog_api/wrapper_tools/CancelRunningSavedQuery.json
arcade_posthog_api/wrapper_tools/CancelSavedQueryWorkflow.json
arcade_posthog_api/wrapper_tools/CheckAsyncAuth.json
arcade_posthog_api/wrapper_tools/CheckDemoDataGenerationStatus.json
arcade_posthog_api/wrapper_tools/CheckPosthogEnvAuthenticationAsync.json
arcade_posthog_api/wrapper_tools/CheckPropertyEventAssociation.json
arcade_posthog_api/wrapper_tools/CompleteProjectOnboarding.json
arcade_posthog_api/wrapper_tools/CompleteSymbolSetUpload.json
arcade_posthog_api/wrapper_tools/CompleteSymbolSetsUpload.json
arcade_posthog_api/wrapper_tools/CountFilesInDirectory.json
arcade_posthog_api/wrapper_tools/CreateAnnotation.json
arcade_posthog_api/wrapper_tools/CreateBackfillForBatchExport.json
arcade_posthog_api/wrapper_tools/CreateBatchExport.json
arcade_posthog_api/wrapper_tools/CreateBatchExportBackfill.json
arcade_posthog_api/wrapper_tools/CreateBatchExportForEnvironments.json
arcade_posthog_api/wrapper_tools/CreateBatchExports.json
arcade_posthog_api-2.0.0.dist-info/METADATA
arcade_posthog_api-2.0.0.dist-info/WHEEL
arcade_posthog_api-2.0.0.dist-info/licenses/LICENSE
arcade_posthog_api-2.0.0.dist-info/RECORD
